.DS_Store
.editorconfig
.gitignore
.travis.yml
AUTHORS.rst
CONTRIBUTING.rst
HISTORY.rst
LICENSE
MANIFEST.in
Makefile
README.rst
make.bat
requirements_dev.txt
setup.cfg
setup.py
shorts.sh
tox.ini
.github/ISSUE_TEMPLATE.md
causalwsnmtes.egg-info/PKG-INFO
causalwsnmtes.egg-info/SOURCES.txt
causalwsnmtes.egg-info/dependency_links.txt
causalwsnmtes.egg-info/entry_points.txt
causalwsnmtes.egg-info/not-zip-safe
causalwsnmtes.egg-info/requires.txt
causalwsnmtes.egg-info/top_level.txt
docs/Makefile
docs/authors.rst
docs/conf.py
docs/contributing.rst
docs/history.rst
docs/index.rst
docs/installation.rst
docs/make.bat
docs/readme.rst
docs/usage.rst
source/conf.py
source/index.rst
tests/__init__.py
tests/test_CPE.py
transformersapp/__init__.py
transformersapp/cli.py
transformersapp/huggingface.py
transformersapp/main.py
transformersapp/timeseriesforecastor
transformersapp/woringtransfoemer.py