Metadata-Version: 2.1
Name: causalwsnmtes
Version: 0.1.1
Summary: Testing the Cookiecutter
Home-page: https://github.com/apargc61/causalwsnmtes
Author: Apar C
Author-email: apargc61@gmail.com
License: MIT license
Keywords: causalwsnmtes
Classifier: Development Status :: 2 - Pre-Alpha
Classifier: Intended Audience :: Developers
Classifier: License :: OSI Approved :: MIT License
Classifier: Natural Language :: English
Classifier: Programming Language :: Python :: 3
Classifier: Programming Language :: Python :: 3.6
Classifier: Programming Language :: Python :: 3.7
Classifier: Programming Language :: Python :: 3.8
Requires-Python: >=3.6
License-File: LICENSE
License-File: AUTHORS.rst
